django_injector/__init__.py
django_injector-0.2.3.dist-info/LICENSE
django_injector-0.2.3.dist-info/METADATA
django_injector-0.2.3.dist-info/WHEEL
django_injector-0.2.3.dist-info/top_level.txt
django_injector-0.2.3.dist-info/RECORD
