Metadata-Version: 2.1
Name: django-injector
Version: 0.2.3
Summary: Integrate injector with Django
Home-page: https://github.com/blubber/django_injector
Author: Tiemo Kieft
Author-email: pypi@isogram.nl
License: UNKNOWN
Platform: UNKNOWN
Classifier: Programming Language :: Python :: 3
Classifier: License :: OSI Approved :: BSD License
Classifier: Operating System :: OS Independent
Requires-Dist: injector
